{
    "code": 0,
    "msg": "接口将在5-10月进行访问调整，为了避免给您的业务带来影响，请留意官网公告或加群895091543获取最新动态",
    "data": {
        "list": [
            {
                "year": 2023,
                "month": 202312,
                "date": 20231225,
                "yearweek": 202352,
                "yearday": 359,
                "lunar_year": 2023,
                "lunar_month": 202311,
                "lunar_date": 20231113,
                "lunar_yearday": 338,
                "week": 1,
                "weekend": 2,
                "workday": 1,
                "holiday": 97,
                "holiday_or": 97,
                "holiday_overtime": 10,
                "holiday_today": 1,
                "holiday_legal": 2,
                "holiday_recess": 2,
                "year_cn": "2023年",
                "month_cn": "2023年12月",
                "date_cn": "2023年12月25日",
                "yearweek_cn": "2023年第52周",
                "yearday_cn": "2023年第359天",
                "lunar_year_cn": "二零二三年",
                "lunar_month_cn": "二零二三年冬月",
                "lunar_date_cn": "二零二三年冬月十三",
                "lunar_yearday_cn": "2023年第338天",
                "week_cn": "星期一",
                "weekend_cn": "非周末",
                "workday_cn": "工作日",
                "holiday_cn": "圣诞节",
                "holiday_or_cn": "圣诞节",
                "holiday_overtime_cn": "非节假日调休",
                "holiday_today_cn": "节日当天",
                "holiday_legal_cn": "非法定节假日",
                "holiday_recess_cn": "非假期节假日"
            },
            {
                "year": 2023,
                "month": 202311,
                "date": 20231127,
                "yearweek": 202348,
                "yearday": 331,
                "lunar_year": 2023,
                "lunar_month": 202310,
                "lunar_date": 20231015,
                "lunar_yearday": 310,
                "week": 1,
                "weekend": 2,
                "workday": 1,
                "holiday": 96,
                "holiday_or": 96,
                "holiday_overtime": 10,
                "holiday_today": 1,
                "holiday_legal": 2,
                "holiday_recess": 2,
                "year_cn": "2023年",
                "month_cn": "2023年11月",
                "date_cn": "2023年11月27日",
                "yearweek_cn": "2023年第48周",
                "yearday_cn": "2023年第331天",
                "lunar_year_cn": "二零二三年",
                "lunar_month_cn": "二零二三年十月",
                "lunar_date_cn": "二零二三年十月十五",
                "lunar_yearday_cn": "2023年第310天",
                "week_cn": "星期一",
                "weekend_cn": "非周末",
                "workday_cn": "工作日",
                "holiday_cn": "下元节",
                "holiday_or_cn": "下元节",
                "holiday_overtime_cn": "非节假日调休",
                "holiday_today_cn": "节日当天",
                "holiday_legal_cn": "非法定节假日",
                "holiday_recess_cn": "非假期节假日"
            },
            {
                "year": 2023,
                "month": 202311,
                "date": 20231123,
                "yearweek": 202347,
                "yearday": 327,
                "lunar_year": 2023,
                "lunar_month": 202310,
                "lunar_date": 20231011,
                "lunar_yearday": 306,
                "week": 4,
                "weekend": 2,
                "workday": 1,
                "holiday": 95,
                "holiday_or": 95,
                "holiday_overtime": 10,
                "holiday_today": 1,
                "holiday_legal": 2,
                "holiday_recess": 2,
                "year_cn": "2023年",
                "month_cn": "2023年11月",
                "date_cn": "2023年11月23日",
                "yearweek_cn": "2023年第47周",
                "yearday_cn": "2023年第327天",
                "lunar_year_cn": "二零二三年",
                "lunar_month_cn": "二零二三年十月",
                "lunar_date_cn": "二零二三年十月十一",
                "lunar_yearday_cn": "2023年第306天",
                "week_cn": "星期四",
                "weekend_cn": "非周末",
                "workday_cn": "工作日",
                "holiday_cn": "感恩节",
                "holiday_or_cn": "感恩节",
                "holiday_overtime_cn": "非节假日调休",
                "holiday_today_cn": "节日当天",
                "holiday_legal_cn": "非法定节假日",
                "holiday_recess_cn": "非假期节假日"
            },
            {
                "year": 2023,
                "month": 202311,
                "date": 20231117,
                "yearweek": 202346,
                "yearday": 321,
                "lunar_year": 2023,
                "lunar_month": 202310,
                "lunar_date": 20231005,
                "lunar_yearday": 300,
                "week": 5,
                "weekend": 2,
                "workday": 1,
                "holiday": 93,
                "holiday_or": 93,
                "holiday_overtime": 10,
                "holiday_today": 1,
                "holiday_legal": 2,
                "holiday_recess": 2,
                "year_cn": "2023年",
                "month_cn": "2023年11月",
                "date_cn": "2023年11月17日",
                "yearweek_cn": "2023年第46周",
                "yearday_cn": "2023年第321天",
                "lunar_year_cn": "二零二三年",
                "lunar_month_cn": "二零二三年十月",
                "lunar_date_cn": "二零二三年十月初五",
                "lunar_yearday_cn": "2023年第300天",
                "week_cn": "星期五",
                "weekend_cn": "非周末",
                "workday_cn": "工作日",
                "holiday_cn": "大学生节",
                "holiday_or_cn": "大学生节",
                "holiday_overtime_cn": "非节假日调休",
                "holiday_today_cn": "节日当天",
                "holiday_legal_cn": "非法定节假日",
                "holiday_recess_cn": "非假期节假日"
            },
            {
                "year": 2023,
                "month": 202311,
                "date": 20231113,
                "yearweek": 202346,
                "yearday": 317,
                "lunar_year": 2023,
                "lunar_month": 202310,
                "lunar_date": 20231001,
                "lunar_yearday": 296,
                "week": 1,
                "weekend": 2,
                "workday": 1,
                "holiday": 92,
                "holiday_or": 92,
                "holiday_overtime": 10,
                "holiday_today": 1,
                "holiday_legal": 2,
                "holiday_recess": 2,
                "year_cn": "2023年",
                "month_cn": "2023年11月",
                "date_cn": "2023年11月13日",
                "yearweek_cn": "2023年第46周",
                "yearday_cn": "2023年第317天",
                "lunar_year_cn": "二零二三年",
                "lunar_month_cn": "二零二三年十月",
                "lunar_date_cn": "二零二三年十月初一",
                "lunar_yearday_cn": "2023年第296天",
                "week_cn": "星期一",
                "weekend_cn": "非周末",
                "workday_cn": "工作日",
                "holiday_cn": "寒衣节",
                "holiday_or_cn": "寒衣节",
                "holiday_overtime_cn": "非节假日调休",
                "holiday_today_cn": "节日当天",
                "holiday_legal_cn": "非法定节假日",
                "holiday_recess_cn": "非假期节假日"
            },
            {
                "year": 2023,
                "month": 202311,
                "date": 20231108,
                "yearweek": 202345,
                "yearday": 312,
                "lunar_year": 2023,
                "lunar_month": 202309,
                "lunar_date": 20230925,
                "lunar_yearday": 291,
                "week": 3,
                "weekend": 2,
                "workday": 1,
                "holiday": 91,
                "holiday_or": 91,
                "holiday_overtime": 10,
                "holiday_today": 1,
                "holiday_legal": 2,
                "holiday_recess": 2,
                "year_cn": "2023年",
                "month_cn": "2023年11月",
                "date_cn": "2023年11月08日",
                "yearweek_cn": "2023年第45周",
                "yearday_cn": "2023年第312天",
                "lunar_year_cn": "二零二三年",
                "lunar_month_cn": "二零二三年九月",
                "lunar_date_cn": "二零二三年九月廿五",
                "lunar_yearday_cn": "2023年第291天",
                "week_cn": "星期三",
                "weekend_cn": "非周末",
                "workday_cn": "工作日",
                "holiday_cn": "记者节",
                "holiday_or_cn": "记者节",
                "holiday_overtime_cn": "非节假日调休",
                "holiday_today_cn": "节日当天",
                "holiday_legal_cn": "非法定节假日",
                "holiday_recess_cn": "非假期节假日"
            },
            {
                "year": 2023,
                "month": 202310,
                "date": 20231023,
                "yearweek": 202343,
                "yearday": 296,
                "lunar_year": 2023,
                "lunar_month": 202309,
                "lunar_date": 20230909,
                "lunar_yearday": 275,
                "week": 1,
                "weekend": 2,
                "workday": 1,
                "holiday": 89,
                "holiday_or": 90,
                "holiday_overtime": 10,
                "holiday_today": 1,
                "holiday_legal": 2,
                "holiday_recess": 2,
                "year_cn": "2023年",
                "month_cn": "2023年10月",
                "date_cn": "2023年10月23日",
                "yearweek_cn": "2023年第43周",
                "yearday_cn": "2023年第296天",
                "lunar_year_cn": "二零二三年",
                "lunar_month_cn": "二零二三年九月",
                "lunar_date_cn": "二零二三年九月初九",
                "lunar_yearday_cn": "2023年第275天",
                "week_cn": "星期一",
                "weekend_cn": "非周末",
                "workday_cn": "工作日",
                "holiday_cn": "重阳节",
                "holiday_or_cn": "老年节",
                "holiday_overtime_cn": "非节假日调休",
                "holiday_today_cn": "节日当天",
                "holiday_legal_cn": "非法定节假日",
                "holiday_recess_cn": "非假期节假日"
            },
            {
                "year": 2023,
                "month": 202310,
                "date": 20231001,
                "yearweek": 202339,
                "yearday": 274,
                "lunar_year": 2023,
                "lunar_month": 202308,
                "lunar_date": 20230817,
                "lunar_yearday": 253,
                "week": 7,
                "weekend": 1,
                "workday": 2,
                "holiday": 88,
                "holiday_or": 88,
                "holiday_overtime": 10,
                "holiday_today": 1,
                "holiday_legal": 1,
                "holiday_recess": 1,
                "year_cn": "2023年",
                "month_cn": "2023年10月",
                "date_cn": "2023年10月01日",
                "yearweek_cn": "2023年第39周",
                "yearday_cn": "2023年第274天",
                "lunar_year_cn": "二零二三年",
                "lunar_month_cn": "二零二三年八月",
                "lunar_date_cn": "二零二三年八月十七",
                "lunar_yearday_cn": "2023年第253天",
                "week_cn": "星期日",
                "weekend_cn": "周末",
                "workday_cn": "非工作日",
                "holiday_cn": "国庆节",
                "holiday_or_cn": "国庆节",
                "holiday_overtime_cn": "非节假日调休",
                "holiday_today_cn": "节日当天",
                "holiday_legal_cn": "法定节假日",
                "holiday_recess_cn": "假期节假日"
            },
            {
                "year": 2023,
                "month": 202309,
                "date": 20230923,
                "yearweek": 202338,
                "yearday": 266,
                "lunar_year": 2023,
                "lunar_month": 202308,
                "lunar_date": 20230809,
                "lunar_yearday": 245,
                "week": 6,
                "weekend": 1,
                "workday": 2,
                "holiday": 78,
                "holiday_or": 78,
                "holiday_overtime": 10,
                "holiday_today": 1,
                "holiday_legal": 2,
                "holiday_recess": 2,
                "year_cn": "2023年",
                "month_cn": "2023年09月",
                "date_cn": "2023年09月23日",
                "yearweek_cn": "2023年第38周",
                "yearday_cn": "2023年第266天",
                "lunar_year_cn": "二零二三年",
                "lunar_month_cn": "二零二三年八月",
                "lunar_date_cn": "二零二三年八月初九",
                "lunar_yearday_cn": "2023年第245天",
                "week_cn": "星期六",
                "weekend_cn": "周末",
                "workday_cn": "非工作日",
                "holiday_cn": "中国农民丰收节",
                "holiday_or_cn": "中国农民丰收节",
                "holiday_overtime_cn": "非节假日调休",
                "holiday_today_cn": "节日当天",
                "holiday_legal_cn": "非法定节假日",
                "holiday_recess_cn": "非假期节假日"
            },
            {
                "year": 2023,
                "month": 202309,
                "date": 20230910,
                "yearweek": 202336,
                "yearday": 253,
                "lunar_year": 2023,
                "lunar_month": 202307,
                "lunar_date": 20230726,
                "lunar_yearday": 232,
                "week": 7,
                "weekend": 1,
                "workday": 2,
                "holiday": 72,
                "holiday_or": 72,
                "holiday_overtime": 10,
                "holiday_today": 1,
                "holiday_legal": 2,
                "holiday_recess": 2,
                "year_cn": "2023年",
                "month_cn": "2023年09月",
                "date_cn": "2023年09月10日",
                "yearweek_cn": "2023年第36周",
                "yearday_cn": "2023年第253天",
                "lunar_year_cn": "二零二三年",
                "lunar_month_cn": "二零二三年七月",
                "lunar_date_cn": "二零二三年七月廿六",
                "lunar_yearday_cn": "2023年第232天",
                "week_cn": "星期日",
                "weekend_cn": "周末",
                "workday_cn": "非工作日",
                "holiday_cn": "教师节",
                "holiday_or_cn": "教师节",
                "holiday_overtime_cn": "非节假日调休",
                "holiday_today_cn": "节日当天",
                "holiday_legal_cn": "非法定节假日",
                "holiday_recess_cn": "非假期节假日"
            },
            {
                "year": 2023,
                "month": 202308,
                "date": 20230830,
                "yearweek": 202335,
                "yearday": 242,
                "lunar_year": 2023,
                "lunar_month": 202307,
                "lunar_date": 20230715,
                "lunar_yearday": 221,
                "week": 3,
                "weekend": 2,
                "workday": 1,
                "holiday": 71,
                "holiday_or": 71,
                "holiday_overtime": 10,
                "holiday_today": 1,
                "holiday_legal": 2,
                "holiday_recess": 2,
                "year_cn": "2023年",
                "month_cn": "2023年08月",
                "date_cn": "2023年08月30日",
                "yearweek_cn": "2023年第35周",
                "yearday_cn": "2023年第242天",
                "lunar_year_cn": "二零二三年",
                "lunar_month_cn": "二零二三年七月",
                "lunar_date_cn": "二零二三年七月十五",
                "lunar_yearday_cn": "2023年第221天",
                "week_cn": "星期三",
                "weekend_cn": "非周末",
                "workday_cn": "工作日",
                "holiday_cn": "中元节",
                "holiday_or_cn": "中元节",
                "holiday_overtime_cn": "非节假日调休",
                "holiday_today_cn": "节日当天",
                "holiday_legal_cn": "非法定节假日",
                "holiday_recess_cn": "非假期节假日"
            },
            {
                "year": 2023,
                "month": 202308,
                "date": 20230822,
                "yearweek": 202334,
                "yearday": 234,
                "lunar_year": 2023,
                "lunar_month": 202307,
                "lunar_date": 20230707,
                "lunar_yearday": 213,
                "week": 2,
                "weekend": 2,
                "workday": 1,
                "holiday": 70,
                "holiday_or": 70,
                "holiday_overtime": 10,
                "holiday_today": 1,
                "holiday_legal": 2,
                "holiday_recess": 2,
                "year_cn": "2023年",
                "month_cn": "2023年08月",
                "date_cn": "2023年08月22日",
                "yearweek_cn": "2023年第34周",
                "yearday_cn": "2023年第234天",
                "lunar_year_cn": "二零二三年",
                "lunar_month_cn": "二零二三年七月",
                "lunar_date_cn": "二零二三年七月初七",
                "lunar_yearday_cn": "2023年第213天",
                "week_cn": "星期二",
                "weekend_cn": "非周末",
                "workday_cn": "工作日",
                "holiday_cn": "七夕节",
                "holiday_or_cn": "七夕节",
                "holiday_overtime_cn": "非节假日调休",
                "holiday_today_cn": "节日当天",
                "holiday_legal_cn": "非法定节假日",
                "holiday_recess_cn": "非假期节假日"
            },
            {
                "year": 2023,
                "month": 202308,
                "date": 20230819,
                "yearweek": 202333,
                "yearday": 231,
                "lunar_year": 2023,
                "lunar_month": 202307,
                "lunar_date": 20230704,
                "lunar_yearday": 210,
                "week": 6,
                "weekend": 1,
                "workday": 2,
                "holiday": 69,
                "holiday_or": 69,
                "holiday_overtime": 10,
                "holiday_today": 1,
                "holiday_legal": 2,
                "holiday_recess": 2,
                "year_cn": "2023年",
                "month_cn": "2023年08月",
                "date_cn": "2023年08月19日",
                "yearweek_cn": "2023年第33周",
                "yearday_cn": "2023年第231天",
                "lunar_year_cn": "二零二三年",
                "lunar_month_cn": "二零二三年七月",
                "lunar_date_cn": "二零二三年七月初四",
                "lunar_yearday_cn": "2023年第210天",
                "week_cn": "星期六",
                "weekend_cn": "周末",
                "workday_cn": "非工作日",
                "holiday_cn": "中国医师节",
                "holiday_or_cn": "中国医师节",
                "holiday_overtime_cn": "非节假日调休",
                "holiday_today_cn": "节日当天",
                "holiday_legal_cn": "非法定节假日",
                "holiday_recess_cn": "非假期节假日"
            },
            {
                "year": 2023,
                "month": 202308,
                "date": 20230801,
                "yearweek": 202331,
                "yearday": 213,
                "lunar_year": 2023,
                "lunar_month": 202306,
                "lunar_date": 20230615,
                "lunar_yearday": 192,
                "week": 2,
                "weekend": 2,
                "workday": 1,
                "holiday": 68,
                "holiday_or": 68,
                "holiday_overtime": 10,
                "holiday_today": 1,
                "holiday_legal": 2,
                "holiday_recess": 2,
                "year_cn": "2023年",
                "month_cn": "2023年08月",
                "date_cn": "2023年08月01日",
                "yearweek_cn": "2023年第31周",
                "yearday_cn": "2023年第213天",
                "lunar_year_cn": "二零二三年",
                "lunar_month_cn": "二零二三年六月",
                "lunar_date_cn": "二零二三年六月十五",
                "lunar_yearday_cn": "2023年第192天",
                "week_cn": "星期二",
                "weekend_cn": "非周末",
                "workday_cn": "工作日",
                "holiday_cn": "建军节",
                "holiday_or_cn": "建军节",
                "holiday_overtime_cn": "非节假日调休",
                "holiday_today_cn": "节日当天",
                "holiday_legal_cn": "非法定节假日",
                "holiday_recess_cn": "非假期节假日"
            },
            {
                "year": 2023,
                "month": 202307,
                "date": 20230701,
                "yearweek": 202326,
                "yearday": 182,
                "lunar_year": 2023,
                "lunar_month": 202305,
                "lunar_date": 20230514,
                "lunar_yearday": 161,
                "week": 6,
                "weekend": 1,
                "workday": 2,
                "holiday": 67,
                "holiday_or": 67,
                "holiday_overtime": 10,
                "holiday_today": 1,
                "holiday_legal": 2,
                "holiday_recess": 2,
                "year_cn": "2023年",
                "month_cn": "2023年07月",
                "date_cn": "2023年07月01日",
                "yearweek_cn": "2023年第26周",
                "yearday_cn": "2023年第182天",
                "lunar_year_cn": "二零二三年",
                "lunar_month_cn": "二零二三年五月",
                "lunar_date_cn": "二零二三年五月十四",
                "lunar_yearday_cn": "2023年第161天",
                "week_cn": "星期六",
                "weekend_cn": "周末",
                "workday_cn": "非工作日",
                "holiday_cn": "建党节",
                "holiday_or_cn": "建党节",
                "holiday_overtime_cn": "非节假日调休",
                "holiday_today_cn": "节日当天",
                "holiday_legal_cn": "非法定节假日",
                "holiday_recess_cn": "非假期节假日"
            },
            {
                "year": 2023,
                "month": 202306,
                "date": 20230622,
                "yearweek": 202325,
                "yearday": 173,
                "lunar_year": 2023,
                "lunar_month": 202305,
                "lunar_date": 20230505,
                "lunar_yearday": 152,
                "week": 4,
                "weekend": 2,
                "workday": 2,
                "holiday": 66,
                "holiday_or": 66,
                "holiday_overtime": 10,
                "holiday_today": 1,
                "holiday_legal": 1,
                "holiday_recess": 1,
                "year_cn": "2023年",
                "month_cn": "2023年06月",
                "date_cn": "2023年06月22日",
                "yearweek_cn": "2023年第25周",
                "yearday_cn": "2023年第173天",
                "lunar_year_cn": "二零二三年",
                "lunar_month_cn": "二零二三年五月",
                "lunar_date_cn": "二零二三年五月初五",
                "lunar_yearday_cn": "2023年第152天",
                "week_cn": "星期四",
                "weekend_cn": "非周末",
                "workday_cn": "非工作日",
                "holiday_cn": "端午节",
                "holiday_or_cn": "端午节",
                "holiday_overtime_cn": "非节假日调休",
                "holiday_today_cn": "节日当天",
                "holiday_legal_cn": "法定节假日",
                "holiday_recess_cn": "假期节假日"
            },
            {
                "year": 2023,
                "month": 202306,
                "date": 20230618,
                "yearweek": 202324,
                "yearday": 169,
                "lunar_year": 2023,
                "lunar_month": 202305,
                "lunar_date": 20230501,
                "lunar_yearday": 148,
                "week": 7,
                "weekend": 1,
                "workday": 2,
                "holiday": 62,
                "holiday_or": 62,
                "holiday_overtime": 10,
                "holiday_today": 1,
                "holiday_legal": 2,
                "holiday_recess": 2,
                "year_cn": "2023年",
                "month_cn": "2023年06月",
                "date_cn": "2023年06月18日",
                "yearweek_cn": "2023年第24周",
                "yearday_cn": "2023年第169天",
                "lunar_year_cn": "二零二三年",
                "lunar_month_cn": "二零二三年五月",
                "lunar_date_cn": "二零二三年五月初一",
                "lunar_yearday_cn": "2023年第148天",
                "week_cn": "星期日",
                "weekend_cn": "周末",
                "workday_cn": "非工作日",
                "holiday_cn": "父亲节",
                "holiday_or_cn": "父亲节",
                "holiday_overtime_cn": "非节假日调休",
                "holiday_today_cn": "节日当天",
                "holiday_legal_cn": "非法定节假日",
                "holiday_recess_cn": "非假期节假日"
            },
            {
                "year": 2023,
                "month": 202306,
                "date": 20230601,
                "yearweek": 202322,
                "yearday": 152,
                "lunar_year": 2023,
                "lunar_month": 202304,
                "lunar_date": 20230414,
                "lunar_yearday": 131,
                "week": 4,
                "weekend": 2,
                "workday": 1,
                "holiday": 61,
                "holiday_or": 61,
                "holiday_overtime": 10,
                "holiday_today": 1,
                "holiday_legal": 2,
                "holiday_recess": 2,
                "year_cn": "2023年",
                "month_cn": "2023年06月",
                "date_cn": "2023年06月01日",
                "yearweek_cn": "2023年第22周",
                "yearday_cn": "2023年第152天",
                "lunar_year_cn": "二零二三年",
                "lunar_month_cn": "二零二三年四月",
                "lunar_date_cn": "二零二三年四月十四",
                "lunar_yearday_cn": "2023年第131天",
                "week_cn": "星期四",
                "weekend_cn": "非周末",
                "workday_cn": "工作日",
                "holiday_cn": "儿童节",
                "holiday_or_cn": "儿童节",
                "holiday_overtime_cn": "非节假日调休",
                "holiday_today_cn": "节日当天",
                "holiday_legal_cn": "非法定节假日",
                "holiday_recess_cn": "非假期节假日"
            },
            {
                "year": 2023,
                "month": 202305,
                "date": 20230514,
                "yearweek": 202319,
                "yearday": 134,
                "lunar_year": 2023,
                "lunar_month": 202303,
                "lunar_date": 20230325,
                "lunar_yearday": 113,
                "week": 7,
                "weekend": 1,
                "workday": 2,
                "holiday": 58,
                "holiday_or": 58,
                "holiday_overtime": 10,
                "holiday_today": 1,
                "holiday_legal": 2,
                "holiday_recess": 2,
                "year_cn": "2023年",
                "month_cn": "2023年05月",
                "date_cn": "2023年05月14日",
                "yearweek_cn": "2023年第19周",
                "yearday_cn": "2023年第134天",
                "lunar_year_cn": "二零二三年",
                "lunar_month_cn": "二零二三年三月",
                "lunar_date_cn": "二零二三年三月廿五",
                "lunar_yearday_cn": "2023年第113天",
                "week_cn": "星期日",
                "weekend_cn": "周末",
                "workday_cn": "非工作日",
                "holiday_cn": "母亲节",
                "holiday_or_cn": "母亲节",
                "holiday_overtime_cn": "非节假日调休",
                "holiday_today_cn": "节日当天",
                "holiday_legal_cn": "非法定节假日",
                "holiday_recess_cn": "非假期节假日"
            },
            {
                "year": 2023,
                "month": 202305,
                "date": 20230512,
                "yearweek": 202319,
                "yearday": 132,
                "lunar_year": 2023,
                "lunar_month": 202303,
                "lunar_date": 20230323,
                "lunar_yearday": 111,
                "week": 5,
                "weekend": 2,
                "workday": 1,
                "holiday": 59,
                "holiday_or": 59,
                "holiday_overtime": 10,
                "holiday_today": 1,
                "holiday_legal": 2,
                "holiday_recess": 2,
                "year_cn": "2023年",
                "month_cn": "2023年05月",
                "date_cn": "2023年05月12日",
                "yearweek_cn": "2023年第19周",
                "yearday_cn": "2023年第132天",
                "lunar_year_cn": "二零二三年",
                "lunar_month_cn": "二零二三年三月",
                "lunar_date_cn": "二零二三年三月廿三",
                "lunar_yearday_cn": "2023年第111天",
                "week_cn": "星期五",
                "weekend_cn": "非周末",
                "workday_cn": "工作日",
                "holiday_cn": "护士节",
                "holiday_or_cn": "护士节",
                "holiday_overtime_cn": "非节假日调休",
                "holiday_today_cn": "节日当天",
                "holiday_legal_cn": "非法定节假日",
                "holiday_recess_cn": "非假期节假日"
            },
            {
                "year": 2023,
                "month": 202305,
                "date": 20230504,
                "yearweek": 202318,
                "yearday": 124,
                "lunar_year": 2023,
                "lunar_month": 202303,
                "lunar_date": 20230315,
                "lunar_yearday": 103,
                "week": 4,
                "weekend": 2,
                "workday": 1,
                "holiday": 56,
                "holiday_or": 56,
                "holiday_overtime": 10,
                "holiday_today": 1,
                "holiday_legal": 2,
                "holiday_recess": 2,
                "year_cn": "2023年",
                "month_cn": "2023年05月",
                "date_cn": "2023年05月04日",
                "yearweek_cn": "2023年第18周",
                "yearday_cn": "2023年第124天",
                "lunar_year_cn": "二零二三年",
                "lunar_month_cn": "二零二三年三月",
                "lunar_date_cn": "二零二三年三月十五",
                "lunar_yearday_cn": "2023年第103天",
                "week_cn": "星期四",
                "weekend_cn": "非周末",
                "workday_cn": "工作日",
                "holiday_cn": "青年节",
                "holiday_or_cn": "青年节",
                "holiday_overtime_cn": "非节假日调休",
                "holiday_today_cn": "节日当天",
                "holiday_legal_cn": "非法定节假日",
                "holiday_recess_cn": "非假期节假日"
            },
            {
                "year": 2023,
                "month": 202305,
                "date": 20230501,
                "yearweek": 202318,
                "yearday": 121,
                "lunar_year": 2023,
                "lunar_month": 202303,
                "lunar_date": 20230312,
                "lunar_yearday": 100,
                "week": 1,
                "weekend": 2,
                "workday": 2,
                "holiday": 55,
                "holiday_or": 55,
                "holiday_overtime": 10,
                "holiday_today": 1,
                "holiday_legal": 1,
                "holiday_recess": 1,
                "year_cn": "2023年",
                "month_cn": "2023年05月",
                "date_cn": "2023年05月01日",
                "yearweek_cn": "2023年第18周",
                "yearday_cn": "2023年第121天",
                "lunar_year_cn": "二零二三年",
                "lunar_month_cn": "二零二三年三月",
                "lunar_date_cn": "二零二三年三月十二",
                "lunar_yearday_cn": "2023年第100天",
                "week_cn": "星期一",
                "weekend_cn": "非周末",
                "workday_cn": "非工作日",
                "holiday_cn": "劳动节",
                "holiday_or_cn": "劳动节",
                "holiday_overtime_cn": "非节假日调休",
                "holiday_today_cn": "节日当天",
                "holiday_legal_cn": "法定节假日",
                "holiday_recess_cn": "假期节假日"
            },
            {
                "year": 2023,
                "month": 202304,
                "date": 20230409,
                "yearweek": 202314,
                "yearday": 99,
                "lunar_year": 2023,
                "lunar_month": 202314,
                "lunar_date": 20231419,
                "lunar_yearday": 78,
                "week": 7,
                "weekend": 1,
                "workday": 2,
                "holiday": 45,
                "holiday_or": 45,
                "holiday_overtime": 10,
                "holiday_today": 1,
                "holiday_legal": 2,
                "holiday_recess": 2,
                "year_cn": "2023年",
                "month_cn": "2023年04月",
                "date_cn": "2023年04月09日",
                "yearweek_cn": "2023年第14周",
                "yearday_cn": "2023年第99天",
                "lunar_year_cn": "二零二三年",
                "lunar_month_cn": "二零二三年闰二月",
                "lunar_date_cn": "二零二三年闰二月十九",
                "lunar_yearday_cn": "2023年第78天",
                "week_cn": "星期日",
                "weekend_cn": "周末",
                "workday_cn": "非工作日",
                "holiday_cn": "复活节",
                "holiday_or_cn": "复活节",
                "holiday_overtime_cn": "非节假日调休",
                "holiday_today_cn": "节日当天",
                "holiday_legal_cn": "非法定节假日",
                "holiday_recess_cn": "非假期节假日"
            },
            {
                "year": 2023,
                "month": 202304,
                "date": 20230405,
                "yearweek": 202314,
                "yearday": 95,
                "lunar_year": 2023,
                "lunar_month": 202314,
                "lunar_date": 20231415,
                "lunar_yearday": 74,
                "week": 3,
                "weekend": 2,
                "workday": 2,
                "holiday": 44,
                "holiday_or": 44,
                "holiday_overtime": 10,
                "holiday_today": 1,
                "holiday_legal": 1,
                "holiday_recess": 1,
                "year_cn": "2023年",
                "month_cn": "2023年04月",
                "date_cn": "2023年04月05日",
                "yearweek_cn": "2023年第14周",
                "yearday_cn": "2023年第95天",
                "lunar_year_cn": "二零二三年",
                "lunar_month_cn": "二零二三年闰二月",
                "lunar_date_cn": "二零二三年闰二月十五",
                "lunar_yearday_cn": "2023年第74天",
                "week_cn": "星期三",
                "weekend_cn": "非周末",
                "workday_cn": "非工作日",
                "holiday_cn": "清明节",
                "holiday_or_cn": "清明节",
                "holiday_overtime_cn": "非节假日调休",
                "holiday_today_cn": "节日当天",
                "holiday_legal_cn": "法定节假日",
                "holiday_recess_cn": "假期节假日"
            },
            {
                "year": 2023,
                "month": 202304,
                "date": 20230401,
                "yearweek": 202313,
                "yearday": 91,
                "lunar_year": 2023,
                "lunar_month": 202314,
                "lunar_date": 20231411,
                "lunar_yearday": 70,
                "week": 6,
                "weekend": 1,
                "workday": 2,
                "holiday": 23,
                "holiday_or": 23,
                "holiday_overtime": 10,
                "holiday_today": 1,
                "holiday_legal": 2,
                "holiday_recess": 2,
                "year_cn": "2023年",
                "month_cn": "2023年04月",
                "date_cn": "2023年04月01日",
                "yearweek_cn": "2023年第13周",
                "yearday_cn": "2023年第91天",
                "lunar_year_cn": "二零二三年",
                "lunar_month_cn": "二零二三年闰二月",
                "lunar_date_cn": "二零二三年闰二月十一",
                "lunar_yearday_cn": "2023年第70天",
                "week_cn": "星期六",
                "weekend_cn": "周末",
                "workday_cn": "非工作日",
                "holiday_cn": "愚人节",
                "holiday_or_cn": "愚人节",
                "holiday_overtime_cn": "非节假日调休",
                "holiday_today_cn": "节日当天",
                "holiday_legal_cn": "非法定节假日",
                "holiday_recess_cn": "非假期节假日"
            },
            {
                "year": 2023,
                "month": 202303,
                "date": 20230312,
                "yearweek": 202310,
                "yearday": 71,
                "lunar_year": 2023,
                "lunar_month": 202302,
                "lunar_date": 20230221,
                "lunar_yearday": 50,
                "week": 7,
                "weekend": 1,
                "workday": 2,
                "holiday": 21,
                "holiday_or": 21,
                "holiday_overtime": 10,
                "holiday_today": 1,
                "holiday_legal": 2,
                "holiday_recess": 2,
                "year_cn": "2023年",
                "month_cn": "2023年03月",
                "date_cn": "2023年03月12日",
                "yearweek_cn": "2023年第10周",
                "yearday_cn": "2023年第71天",
                "lunar_year_cn": "二零二三年",
                "lunar_month_cn": "二零二三年二月",
                "lunar_date_cn": "二零二三年二月廿一",
                "lunar_yearday_cn": "2023年第50天",
                "week_cn": "星期日",
                "weekend_cn": "周末",
                "workday_cn": "非工作日",
                "holiday_cn": "植树节",
                "holiday_or_cn": "植树节",
                "holiday_overtime_cn": "非节假日调休",
                "holiday_today_cn": "节日当天",
                "holiday_legal_cn": "非法定节假日",
                "holiday_recess_cn": "非假期节假日"
            },
            {
                "year": 2023,
                "month": 202303,
                "date": 20230308,
                "yearweek": 202310,
                "yearday": 67,
                "lunar_year": 2023,
                "lunar_month": 202302,
                "lunar_date": 20230217,
                "lunar_yearday": 46,
                "week": 3,
                "weekend": 2,
                "workday": 1,
                "holiday": 19,
                "holiday_or": 19,
                "holiday_overtime": 10,
                "holiday_today": 1,
                "holiday_legal": 2,
                "holiday_recess": 2,
                "year_cn": "2023年",
                "month_cn": "2023年03月",
                "date_cn": "2023年03月08日",
                "yearweek_cn": "2023年第10周",
                "yearday_cn": "2023年第67天",
                "lunar_year_cn": "二零二三年",
                "lunar_month_cn": "二零二三年二月",
                "lunar_date_cn": "二零二三年二月十七",
                "lunar_yearday_cn": "2023年第46天",
                "week_cn": "星期三",
                "weekend_cn": "非周末",
                "workday_cn": "工作日",
                "holiday_cn": "妇女节",
                "holiday_or_cn": "妇女节",
                "holiday_overtime_cn": "非节假日调休",
                "holiday_today_cn": "节日当天",
                "holiday_legal_cn": "非法定节假日",
                "holiday_recess_cn": "非假期节假日"
            },
            {
                "year": 2023,
                "month": 202302,
                "date": 20230221,
                "yearweek": 202308,
                "yearday": 52,
                "lunar_year": 2023,
                "lunar_month": 202302,
                "lunar_date": 20230202,
                "lunar_yearday": 31,
                "week": 2,
                "weekend": 2,
                "workday": 1,
                "holiday": 18,
                "holiday_or": 18,
                "holiday_overtime": 10,
                "holiday_today": 1,
                "holiday_legal": 2,
                "holiday_recess": 2,
                "year_cn": "2023年",
                "month_cn": "2023年02月",
                "date_cn": "2023年02月21日",
                "yearweek_cn": "2023年第08周",
                "yearday_cn": "2023年第52天",
                "lunar_year_cn": "二零二三年",
                "lunar_month_cn": "二零二三年二月",
                "lunar_date_cn": "二零二三年二月初二",
                "lunar_yearday_cn": "2023年第31天",
                "week_cn": "星期二",
                "weekend_cn": "非周末",
                "workday_cn": "工作日",
                "holiday_cn": "龙头节",
                "holiday_or_cn": "龙头节",
                "holiday_overtime_cn": "非节假日调休",
                "holiday_today_cn": "节日当天",
                "holiday_legal_cn": "非法定节假日",
                "holiday_recess_cn": "非假期节假日"
            },
            {
                "year": 2023,
                "month": 202302,
                "date": 20230214,
                "yearweek": 202307,
                "yearday": 45,
                "lunar_year": 2023,
                "lunar_month": 202301,
                "lunar_date": 20230124,
                "lunar_yearday": 24,
                "week": 2,
                "weekend": 2,
                "workday": 1,
                "holiday": 17,
                "holiday_or": 17,
                "holiday_overtime": 10,
                "holiday_today": 1,
                "holiday_legal": 2,
                "holiday_recess": 2,
                "year_cn": "2023年",
                "month_cn": "2023年02月",
                "date_cn": "2023年02月14日",
                "yearweek_cn": "2023年第07周",
                "yearday_cn": "2023年第45天",
                "lunar_year_cn": "二零二三年",
                "lunar_month_cn": "二零二三年正月",
                "lunar_date_cn": "二零二三年正月廿四",
                "lunar_yearday_cn": "2023年第24天",
                "week_cn": "星期二",
                "weekend_cn": "非周末",
                "workday_cn": "工作日",
                "holiday_cn": "情人节",
                "holiday_or_cn": "情人节",
                "holiday_overtime_cn": "非节假日调休",
                "holiday_today_cn": "节日当天",
                "holiday_legal_cn": "非法定节假日",
                "holiday_recess_cn": "非假期节假日"
            },
            {
                "year": 2023,
                "month": 202302,
                "date": 20230205,
                "yearweek": 202305,
                "yearday": 36,
                "lunar_year": 2023,
                "lunar_month": 202301,
                "lunar_date": 20230115,
                "lunar_yearday": 15,
                "week": 7,
                "weekend": 1,
                "workday": 2,
                "holiday": 16,
                "holiday_or": 16,
                "holiday_overtime": 10,
                "holiday_today": 1,
                "holiday_legal": 2,
                "holiday_recess": 2,
                "year_cn": "2023年",
                "month_cn": "2023年02月",
                "date_cn": "2023年02月05日",
                "yearweek_cn": "2023年第05周",
                "yearday_cn": "2023年第36天",
                "lunar_year_cn": "二零二三年",
                "lunar_month_cn": "二零二三年正月",
                "lunar_date_cn": "二零二三年正月十五",
                "lunar_yearday_cn": "2023年第15天",
                "week_cn": "星期日",
                "weekend_cn": "周末",
                "workday_cn": "非工作日",
                "holiday_cn": "元宵节",
                "holiday_or_cn": "元宵节",
                "holiday_overtime_cn": "非节假日调休",
                "holiday_today_cn": "节日当天",
                "holiday_legal_cn": "非法定节假日",
                "holiday_recess_cn": "非假期节假日"
            },
            {
                "year": 2023,
                "month": 202301,
                "date": 20230122,
                "yearweek": 202303,
                "yearday": 22,
                "lunar_year": 2023,
                "lunar_month": 202301,
                "lunar_date": 20230101,
                "lunar_yearday": 1,
                "week": 7,
                "weekend": 1,
                "workday": 2,
                "holiday": 11,
                "holiday_or": 11,
                "holiday_overtime": 10,
                "holiday_today": 1,
                "holiday_legal": 1,
                "holiday_recess": 1,
                "year_cn": "2023年",
                "month_cn": "2023年01月",
                "date_cn": "2023年01月22日",
                "yearweek_cn": "2023年第03周",
                "yearday_cn": "2023年第22天",
                "lunar_year_cn": "二零二三年",
                "lunar_month_cn": "二零二三年正月",
                "lunar_date_cn": "二零二三年正月初一",
                "lunar_yearday_cn": "2023年第1天",
                "week_cn": "星期日",
                "weekend_cn": "周末",
                "workday_cn": "非工作日",
                "holiday_cn": "春节",
                "holiday_or_cn": "春节",
                "holiday_overtime_cn": "非节假日调休",
                "holiday_today_cn": "节日当天",
                "holiday_legal_cn": "法定节假日",
                "holiday_recess_cn": "假期节假日"
            }
        ],
        "page": 1,
        "size": 31,
        "total": 34
    }
}